{
    "course": [
      {
        "id": "1",
        "category": "engineering",
        "title": "The Data Science Course: Complete Data Science Bootcamp 2024",
  
        "price": "500"
       
      },
      {
        "id": "2",
        "category": "science",
        "title": "Data Science Course: Complete Data Science Bootcamp 2024",
  
        "price": "500"
       
      },
      {
        "id": "3",
        "category": "science",
        "title": "The Data Science Course: Complete Data Science Bootcamp 2024",
  
        "price": "400"
       
      },
      {
        "id": "4",
        "category": "management",
        "title": "The Data Science Course: Complete Data Science Bootcamp 2024",
  
        "price": "800"
     
      }
    ]
  }
  